wagtailsnippetscopy/__init__.py
wagtailsnippetscopy/admin.py
wagtailsnippetscopy/apps.py
wagtailsnippetscopy/forms.py
wagtailsnippetscopy/models.py
wagtailsnippetscopy/registry.py
wagtailsnippetscopy/templates/wagtailsnippetscopy/copy.html
wagtailsnippetscopy/views.py
wagtailsnippetscopy/wagtail_hooks.py
wagtailsnippetscopy-0.5.2.dist-info/METADATA
wagtailsnippetscopy-0.5.2.dist-info/WHEEL
wagtailsnippetscopy-0.5.2.dist-info/RECORD
