Metadata-Version: 2.1
Name: wagtailsnippetscopy
Version: 0.5.2
Summary: Copy A Snippet Feature for Wagtail CMS
Home-page: https://timonweb.com
License: The MIT License (MIT)
Author: Tim Kamanin
Author-email: tim@timonweb.com
Requires-Python: >=3.7,<4.0
Classifier: Development Status :: 4 - Beta
Classifier: Environment :: Web Environment
Classifier: Framework :: Django
Classifier: Intended Audience :: Developers
Classifier: License :: OSI Approved :: Apache Software License
Classifier: License :: Other/Proprietary License
Classifier: Operating System :: OS Independent
Classifier: Programming Language :: Python :: 3
Classifier: Programming Language :: Python :: 3.7
Classifier: Programming Language :: Python :: 3.8
Classifier: Programming Language :: Python :: 3.9
Classifier: Programming Language :: Python :: 3.10
Classifier: Programming Language :: Python :: 3.11
Classifier: Programming Language :: Python :: 3.10
Classifier: Programming Language :: Python :: 3.7
Classifier: Programming Language :: Python :: 3.8
Classifier: Programming Language :: Python :: 3.9
Classifier: Topic :: Software Development :: Libraries
Classifier: Topic :: Utilities
Requires-Dist: django (>=4.0)
Requires-Dist: wagtail (>=4.0)
Project-URL: Repository, https://github.com/timonweb/wagtailsnippetscopy
